snppy/__init__.py
snppy/_version.py
snppy-0.1.2.dist-info/LICENSE.md
snppy-0.1.2.dist-info/METADATA
snppy-0.1.2.dist-info/WHEEL
snppy-0.1.2.dist-info/top_level.txt
snppy-0.1.2.dist-info/RECORD
