Metadata-Version: 2.1
Name: snppy
Version: 0.1.2
Summary: Codebase for running common variant association analyses.
Home-page: https://github.com/alpha-team-genetics/snppy
Author: Tarjinder Singh
Author-email: tsingh@broadinstitute.org
License: MIT license
Platform: UNKNOWN
Requires-Python: >=3.7
License-File: LICENSE.md
Requires-Dist: autopep8 (==1.5.4)
Requires-Dist: versioneer (>=0.18)
Requires-Dist: logzero (==1.5.0)
Requires-Dist: datatracker (>=0.2.0)
Requires-Dist: hail (>=0.2.61)
Requires-Dist: slack-sdk
Requires-Dist: findhere (>=0.1.2)
